RapidML/__init__.py
RapidML-1.0.2.dist-info/METADATA
RapidML-1.0.2.dist-info/RECORD
RapidML-1.0.2.dist-info/WHEEL
RapidML-1.0.2.dist-info/top_level.txt
